[{"index": 0, "precision": "0.64957094", "recall": "0.7874591", "f1": "0.7118996"}, {"index": 1, "precision": "0.7107435", "recall": "0.81956565", "f1": "0.7612853"}, {"index": 2, "precision": "0.82789195", "recall": "0.8794979", "f1": "0.852915"}, {"index": 3, "precision": "0.68552816", "recall": "0.79333097", "f1": "0.73550034"}, {"index": 4, "precision": "0.8050668", "recall": "0.8653145", "f1": "0.8341041"}, {"index": 5, "precision": "0.8211524", "recall": "0.8507451", "f1": "0.83568686"}, {"index": 6, "precision": "0.8153672", "recall": "0.88535166", "f1": "0.8489195"}, {"index": 7, "precision": "0.8809002", "recall": "0.8785167", "f1": "0.8797068"}, {"index": 8, "precision": "0.701096", "recall": "0.79572046", "f1": "0.7454173"}, {"index": 9, "precision": "0.70398766", "recall": "0.79042375", "f1": "0.744706"}, {"index": 10, "precision": "0.81356084", "recall": "0.8689071", "f1": "0.8403236"}, {"index": 11, "precision": "0.6327951", "recall": "0.795213", "f1": "0.7047675"}, {"index": 12, "precision": "0.6249081", "recall": "0.7896373", "f1": "0.69768107"}, {"index": 13, "precision": "0.81694335", "recall": "0.8648083", "f1": "0.84019464"}, {"index": 14, "precision": "0.83785063", "recall": "0.88822925", "f1": "0.86230475"}, {"index": 15, "precision": "0.772493", "recall": "0.8326549", "f1": "0.8014465"}, {"index": 16, "precision": "0.79445934", "recall": "0.86213964", "f1": "0.82691693"}]